ledgerblue/BleComm.py
ledgerblue/BlueHSMServer_pb2.py
ledgerblue/Dongle.py
ledgerblue/__init__.py
ledgerblue/__version__.py
ledgerblue/checkGenuine.py
ledgerblue/checkGenuineRemote.py
ledgerblue/comm.py
ledgerblue/commException.py
ledgerblue/commHTTP.py
ledgerblue/commTCP.py
ledgerblue/commU2F.py
ledgerblue/deleteApp.py
ledgerblue/deployed.py
ledgerblue/derivePassphrase.py
ledgerblue/ecWrapper.py
ledgerblue/endorsementSetup.py
ledgerblue/endorsementSetupLedger.py
ledgerblue/endorsementSetupLedger2.py
ledgerblue/genCAPair.py
ledgerblue/getMemInfo.py
ledgerblue/hashApp.py
ledgerblue/hexLoader.py
ledgerblue/hexParser.py
ledgerblue/hostOnboard.py
ledgerblue/ledgerWrapper.py
ledgerblue/listApps.py
ledgerblue/loadApp.py
ledgerblue/loadMCU.py
ledgerblue/mcuBootloader.py
ledgerblue/readElfMetadata.py
ledgerblue/recoverBackup.py
ledgerblue/recoverDeleteBackup.py
ledgerblue/recoverDeleteCA.py
ledgerblue/recoverMutualAuth.py
ledgerblue/recoverRestore.py
ledgerblue/recoverSCP.py
ledgerblue/recoverSetCA.py
ledgerblue/recoverUtil.py
ledgerblue/resetCustomCA.py
ledgerblue/runApp.py
ledgerblue/runScript.py
ledgerblue/setupCustomCA.py
ledgerblue/signApp.py
ledgerblue/updateFirmware.py
ledgerblue/updateFirmware2.py
ledgerblue/verifyApp.py
ledgerblue/verifyEndorsement1.py
ledgerblue/verifyEndorsement2.py
ledgerblue/vss.py
ledgerblue-0.1.55.dist-info/licenses/LICENSE
ledgerblue-0.1.55.dist-info/METADATA
ledgerblue-0.1.55.dist-info/WHEEL
ledgerblue-0.1.55.dist-info/top_level.txt
ledgerblue-0.1.55.dist-info/RECORD
