Metadata-Version: 2.4
Name: ledgerblue
Version: 0.1.55
Summary: Python library to communicate with Ledger devices
Author-email: Ledger <hello@ledger.fr>
License:                                  Apache License
Project-URL: Home, https://github.com/LedgerHQ/blue-loader-python
Classifier: License :: OSI Approved :: Apache Software License
Classifier: Operating System :: POSIX :: Linux
Classifier: Operating System :: Microsoft :: Windows
Classifier: Operating System :: MacOS :: MacOS X
Classifier: Programming Language :: Python :: 3
Classifier: Programming Language :: Python :: 3 :: Only
Classifier: Programming Language :: Python :: 3.8
Classifier: Programming Language :: Python :: 3.9
Classifier: Programming Language :: Python :: 3.10
Classifier: Programming Language :: Python :: 3.11
Classifier: Programming Language :: Python :: 3.12
Classifier: Programming Language :: Python :: 3.13
Requires-Python: >=3.8
License-File: LICENSE
Requires-Dist: pyelftools<1.0,>=0.29
Requires-Dist: hidapi>=0.7.99
Requires-Dist: protobuf>=5
Requires-Dist: pycryptodomex>=3.6.1
Requires-Dist: future
Requires-Dist: ecpy>=0.9.0
Requires-Dist: pillow>=3.4.0
Requires-Dist: python-u2flib-host>=3.0.2
Requires-Dist: websocket_client>=0.56.0
Requires-Dist: nfcpy>=1.0.4
Requires-Dist: bleak>=0.20.1
Requires-Dist: pycryptodome>=3.18.0
Requires-Dist: python-gnupg>=0.5.0
Provides-Extra: smartcard
Requires-Dist: python-pyscard>=1.6.12; extra == "smartcard"
Provides-Extra: doc
Requires-Dist: sphinx; extra == "doc"
Requires-Dist: sphinx_rtd_theme; extra == "doc"
Requires-Dist: sphinx_argparse; extra == "doc"
Dynamic: license-file
